{
  "greeting": "Hey",
  "name": "Rameel Ahmed Khan",
  "greetingText": "I really like your name btw!",
  "wishText": "My Special ;)",
  "imagePath": "img/rameel.png",
  "text1": "It's your birthday!!! :D",
  "textInChatBox": "Happy Birthday, Rameel Ahmed Khan! 🎉 May your day be as special as you are, filled with love, laughter, and all the things that make you happiest. Here's to celebrating you! 🎂✨",
  "sendButtonLabel": "Send",
  "text2": "That's what I was going to do.",
  "text3": "But then I stopped.",
  "text4": "I realised, I wanted to do something",
  "text4Adjective": "special",
  "text5Entry": "Because,",
  "text5Content": "You are Special",
  "smiley": ":)",
  "bigTextPart1": "S",
  "bigTextPart2": "O",
  "wishHeading": "Happy Birthday!"
}
